AnumbyMasterMind/__init__.py
AnumbyMasterMind/__main__.py
AnumbyMasterMind-1.1.1.dist-info/LICENSE
AnumbyMasterMind-1.1.1.dist-info/METADATA
AnumbyMasterMind-1.1.1.dist-info/WHEEL
AnumbyMasterMind-1.1.1.dist-info/entry_points.txt
AnumbyMasterMind-1.1.1.dist-info/top_level.txt
AnumbyMasterMind-1.1.1.dist-info/RECORD
