Metadata-Version: 2.1
Name: AnumbyMasterMind
Version: 1.1.1
Summary: Implémentation du jeu MasterMind pour être associé avec un Robot et une logique neuronale
Home-page: https://github.com/anumby-source/AnumbyMasterMind
Author: Chris Arnault
Author-email: chris.arnault.1@gmail.com
License: CeCILL-B
Classifier: License :: CeCILL-B Free Software License Agreement (CECILL-B)
Classifier: Programming Language :: Python :: 3
License-File: LICENSE
Requires-Dist: opencv-python (==4.7.0.72)
Requires-Dist: easyocr (==1.7.1)
